odoo/addons/so_sequence_confirmed_order_type/README.rst
odoo/addons/so_sequence_confirmed_order_type/__init__.py
odoo/addons/so_sequence_confirmed_order_type/__manifest__.py
odoo/addons/so_sequence_confirmed_order_type/i18n/es.po
odoo/addons/so_sequence_confirmed_order_type/models/__init__.py
odoo/addons/so_sequence_confirmed_order_type/models/sale_order.py
odoo/addons/so_sequence_confirmed_order_type/models/sale_order_type.py
odoo/addons/so_sequence_confirmed_order_type/static/description/icon.png
odoo/addons/so_sequence_confirmed_order_type/views/sale_order_type_views.xml
odoo_addon_so_sequence_confirmed_order_type-15.0.1.0.0.2.dist-info/METADATA
odoo_addon_so_sequence_confirmed_order_type-15.0.1.0.0.2.dist-info/WHEEL
odoo_addon_so_sequence_confirmed_order_type-15.0.1.0.0.2.dist-info/top_level.txt
odoo_addon_so_sequence_confirmed_order_type-15.0.1.0.0.2.dist-info/RECORD
